setup.py
main/__init__.py
main/case_notes_suggestion.py
main/run.py
main/setup.py
testflask1.egg-info/PKG-INFO
testflask1.egg-info/SOURCES.txt
testflask1.egg-info/dependency_links.txt
testflask1.egg-info/not-zip-safe
testflask1.egg-info/requires.txt
testflask1.egg-info/top_level.txt