Metadata-Version: 1.0
Name: testflask1
Version: 0.1
Summary: testflask1 dependency
Home-page: https://github.com/pypa/testflask1
Author: Tejashree Jaagtap
Author-email: tjagtap@apple.com
License: Apple
Platform: UNKNOWN
